funoptimze/__init__.py
funoptimze/linearsys.py
funoptimze/multidimension.py
funoptimze/unidimension.py
funoptimze-0.1.dist-info/METADATA
funoptimze-0.1.dist-info/WHEEL
funoptimze-0.1.dist-info/top_level.txt
funoptimze-0.1.dist-info/RECORD
