Metadata-Version: 2.1
Name: funoptimze
Version: 0.1
Summary: this is a package with a lot of method of optimization
Home-page: UNKNOWN
Author: Ahmed Mrabet
Author-email: ahmedmrabet.002@gmail.com
License: UNKNOWN
Platform: UNKNOWN
Classifier: Programming Language :: Python :: 3
Classifier: License :: OSI Approved :: MIT License
Classifier: Operating System :: OS Independent
